orient_ficc_pricer/__init__.py
orient_ficc_pricer/base_function/__init__.py
orient_ficc_pricer/base_function/base_pricer.py
orient_ficc_pricer/base_function/protos.py
orient_ficc_pricer/binary/__init__.py
orient_ficc_pricer/binary/binary.py
orient_ficc_pricer/vanilla/__init__.py
orient_ficc_pricer/vanilla/vanilla.py
orient_ficc_pricer-0.0.1.dist-info/METADATA
orient_ficc_pricer-0.0.1.dist-info/WHEEL
orient_ficc_pricer-0.0.1.dist-info/top_level.txt
orient_ficc_pricer-0.0.1.dist-info/RECORD
