Metadata-Version: 2.4
Name: orient_ficc_pricer
Version: 0.0.1
Summary: orient securities ficc option pricing module
Author: zhanghongyu
Platform: any
Requires-Python: >=3.7
Requires-Dist: numpy
Requires-Dist: scipy
Requires-Dist: pandas
Requires-Dist: numba_stats
Dynamic: author
Dynamic: platform
Dynamic: requires-dist
Dynamic: requires-python
Dynamic: summary
